pisinger_cpp.cpython-311-x86_64-linux-gnu.so
parallel_ea.cpython-311-x86_64-linux-gnu.so
digneapy/__init__.py
digneapy/generators.py
digneapy/domains/__init__.py
digneapy/domains/kp.py
digneapy/domains/bpp.py
digneapy/operators/_selection.py
digneapy/operators/_crossover.py
digneapy/operators/__init__.py
digneapy/operators/_replacement.py
digneapy/operators/_mutation.py
digneapy/archives/_base_archive.py
digneapy/archives/__init__.py
digneapy/archives/_cvt_archive.py
digneapy/archives/_grid_archive.py
digneapy/visualize/_evo_generator_evolution_plot.py
digneapy/visualize/__init__.py
digneapy/visualize/_map_elites_evolution_plot.py
digneapy/solvers/pisinger.py
digneapy/solvers/__init__.py
digneapy/solvers/kp.py
digneapy/solvers/evolutionary.py
digneapy/solvers/bpp.py
digneapy/solvers/_pisinger/CMakeLists.txt
digneapy/solvers/_pisinger/src/combo.cpp
digneapy/solvers/_pisinger/src/expknap.cpp
digneapy/solvers/_pisinger/src/minknap.cpp
digneapy/solvers/_pisinger/src/pisinger.cpp
digneapy/solvers/_parallel_ea/CMakeLists.txt
digneapy/solvers/_parallel_ea/src/RandomGenerator.h
digneapy/solvers/_parallel_ea/src/PseudoRandom.h
digneapy/solvers/_parallel_ea/src/parallel_ea.cpp
digneapy/_core/_solver.py
digneapy/_core/_constants.py
digneapy/_core/descriptors.py
digneapy/_core/__init__.py
digneapy/_core/scores.py
digneapy/_core/_instance.py
digneapy/_core/_problem.py
digneapy/_core/_domain.py
digneapy/_core/_novelty_search.py
digneapy/_core/_solution.py
digneapy/transformers/neural.py
digneapy/transformers/__init__.py
digneapy/transformers/_base.py
digneapy/transformers/autoencoders.py
digneapy/transformers/tuner.py
digneapy/transformers/models/pipeline_scaler_autoencoder_N_1000.sav
digneapy/transformers/models/pipeline_scaler_autoencoder_N_50.sav
digneapy/transformers/models/pipeline_scaler_autoencoder_N_250.sav
digneapy/transformers/models/pipeline_scaler_autoencoder_N_var_8d.sav
digneapy-0.2.5.dist-info/top_level.txt
digneapy-0.2.5.dist-info/RECORD
digneapy-0.2.5.dist-info/LICENSE
digneapy-0.2.5.dist-info/AUTHORS.md
digneapy-0.2.5.dist-info/METADATA
digneapy-0.2.5.dist-info/WHEEL
