Metadata-Version: 2.1
Name: digneapy
Version: 0.2.5
Summary: Python version of the DIGNEA code for instance generation
Home-page: https://github.com/DIGNEA/digneapy
Author: Alejandro Marrero
Author-email: Alejandro Marrero <amarrerd@ull.edu.es>
License: GNU GENERAL PUBLIC LICENSE
Project-URL: homepage, https://github.com/DIGNEA/DIGNEApy
Project-URL: source, https://github.com/DIGNEA/DIGNEApy
Project-URL: issues, https://github.com/DIGNEA/DIGNEApy/issues
Keywords: dignea,optimization,instance generation,quality-diversity,NS
Platform: any
Classifier: Development Status :: 2 - Pre-Alpha
Classifier: Intended Audience :: Science/Research
Classifier: Intended Audience :: Developers
Classifier: License :: OSI Approved :: GNU General Public License v3 (GPLv3)
Classifier: Natural Language :: English
Classifier: Programming Language :: Python :: 3
Classifier: Programming Language :: Python :: 3.11
Classifier: Programming Language :: Python :: 3.12
Classifier: Topic :: Scientific/Engineering
Classifier: Typing :: Typed
Classifier: Operating System :: Unix
Classifier: Operating System :: MacOS
Requires-Python: >=3.10
License-File: LICENSE
License-File: AUTHORS.md
Requires-Dist: keras>=3.5.0
Requires-Dist: pandas>=2.2.2
Requires-Dist: deap>=1.4
Requires-Dist: numpy>=2.1.0
Requires-Dist: scikit-learn==1.5.0
Requires-Dist: scipy>=1.13.0
Requires-Dist: torch>=2.3.0
Requires-Dist: pybind11>=2.12.0
Requires-Dist: seaborn>=0.13.2
Requires-Dist: matplotlib>=3.8.4
Provides-Extra: test
Requires-Dist: pytest>=3; extra == "test"
